CHANGES
MANIFEST.in
Makefile
README.md
requirements.txt
setup.py
qcloud/__init__.py
qcloud.egg-info/PKG-INFO
qcloud.egg-info/SOURCES.txt
qcloud.egg-info/dependency_links.txt
qcloud.egg-info/top_level.txt