Metadata-Version: 1.0
Name: qcloud
Version: 0.0.1
Summary: qcloud
Home-page: http://git.agutong.com/dev/qcloud
Author: dev
Author-email: dev@agutong.com
License: LICENSE
Platform: UNKNOWN
